mfournisseur/Fournisseur.py
mfournisseur/__init__.py
biblioFournisseur-1.0.dist-info/METADATA
biblioFournisseur-1.0.dist-info/WHEEL
biblioFournisseur-1.0.dist-info/top_level.txt
biblioFournisseur-1.0.dist-info/RECORD
